atools/__init__.py
atools/_memoize_decorator.py
atools/_rate_decorator.py
atools-0.14.2.dist-info/LICENSE
atools-0.14.2.dist-info/METADATA
atools-0.14.2.dist-info/WHEEL
atools-0.14.2.dist-info/top_level.txt
atools-0.14.2.dist-info/RECORD
