Metadata-Version: 2.1
Name: atools
Version: 0.14.2
Summary: Python 3.6+ async/sync memoize and rate decorators
Home-page: https://github.com/cevans87/atools
Author: cevans
Author-email: c.d.evans87@gmail.com
License: mit
Platform: UNKNOWN
Requires-Python: >=3.6
License-File: LICENSE
Requires-Dist: frozendict
Requires-Dist: dataclasses (>=0.6) ; python_version == "3.6"
